{"kind": "metadata", "pytorch_version": "2.5.1+cu121", "cuda_version": "12.1", "cudnn_version": 90100, "seed": 42, "timestamp": "2026-07-14T22:11:17.302450", "config_file": "configs/profiling.yaml", "device_name": "NVIDIA GeForce RTX 4090", "device_capability": [8, 9]}
{"kind": "layer", "kernel_size": 2, "in_ch": 16, "out_ch": 16, "batch_size": 1, "input_resolution": 64, "precision": "fp32", "latency_ms": 0.030046701431274414, "winograd_speedup_info": {"speedup_ratio": 1.2578829760820989, "winograd_inferred": false}, "device": "nvidia_geforce_rtx_4090_tupi5"}
{"kind": "layer", "kernel_size": 2, "in_ch": 16, "out_ch": 16, "batch_size": 1, "input_resolution": 64, "precision": "int8", "latency_ms": 0.029971599578857422, "winograd_speedup_info": {"speedup_ratio": 1.2601687129374426, "winograd_inferred": false}, "device": "nvidia_geforce_rtx_4090_tupi5"}
{"kind": "layer", "kernel_size": 2, "in_ch": 16, "out_ch": 16, "batch_size": 1, "input_resolution": 128, "precision": "fp32", "latency_ms": 0.03063678741455078, "winograd_speedup_info": {"speedup_ratio": 1.2351691452851774, "winograd_inferred": false}, "device": "nvidia_geforce_rtx_4090_tupi5"}
{"kind": "layer", "kernel_size": 2, "in_ch": 16, "out_ch": 16, "batch_size": 1, "input_resolution": 128, "precision": "int8", "latency_ms": 0.030400753021240234, "winograd_speedup_info": {"speedup_ratio": 1.2395234182415777, "winograd_inferred": false}, "device": "nvidia_geforce_rtx_4090_tupi5"}
{"kind": "layer", "kernel_size": 2, "in_ch": 16, "out_ch": 16, "batch_size": 8, "input_resolution": 64, "precision": "fp32", "latency_ms": 0.03079533576965332, "winograd_speedup_info": {"speedup_ratio": 1.79390253923905, "winograd_inferred": false}, "device": "nvidia_geforce_rtx_4090_tupi5"}
{"kind": "layer", "kernel_size": 2, "in_ch": 16, "out_ch": 16, "batch_size": 8, "input_resolution": 64, "precision": "int8", "latency_ms": 0.030694007873535156, "winograd_speedup_info": {"speedup_ratio": 1.7914579055441477, "winograd_inferred": false}, "device": "nvidia_geforce_rtx_4090_tupi5"}
{"kind": "layer", "kernel_size": 2, "in_ch": 16, "out_ch": 16, "batch_size": 8, "input_resolution": 128, "precision": "fp32", "latency_ms": 0.030934810638427734, "winograd_speedup_info": {"speedup_ratio": 2.22027839050734, "winograd_inferred": true}, "device": "nvidia_geforce_rtx_4090_tupi5"}
{"kind": "layer", "kernel_size": 2, "in_ch": 16, "out_ch": 16, "batch_size": 8, "input_resolution": 128, "precision": "int8", "latency_ms": 0.030614137649536133, "winograd_speedup_info": {"speedup_ratio": 2.223127904319342, "winograd_inferred": true}, "device": "nvidia_geforce_rtx_4090_tupi5"}
{"kind": "layer", "kernel_size": 2, "in_ch": 32, "out_ch": 32, "batch_size": 1, "input_resolution": 64, "precision": "fp32", "latency_ms": 0.030684471130371094, "winograd_speedup_info": {"speedup_ratio": 1.2649530400395452, "winograd_inferred": false}, "device": "nvidia_geforce_rtx_4090_tupi5"}
{"kind": "layer", "kernel_size": 2, "in_ch": 32, "out_ch": 32, "batch_size": 1, "input_resolution": 64, "precision": "int8", "latency_ms": 0.030517578125, "winograd_speedup_info": {"speedup_ratio": 1.2645750988142292, "winograd_inferred": false}, "device": "nvidia_geforce_rtx_4090_tupi5"}
{"kind": "layer", "kernel_size": 2, "in_ch": 32, "out_ch": 32, "batch_size": 1, "input_resolution": 128, "precision": "fp32", "latency_ms": 0.030592679977416992, "winograd_speedup_info": {"speedup_ratio": 1.2272505687357815, "winograd_inferred": false}, "device": "nvidia_geforce_rtx_4090_tupi5"}
{"kind": "layer", "kernel_size": 2, "in_ch": 32, "out_ch": 32, "batch_size": 1, "input_resolution": 128, "precision": "int8", "latency_ms": 0.03063797950744629, "winograd_speedup_info": {"speedup_ratio": 1.2430781758957654, "winograd_inferred": false}, "device": "nvidia_geforce_rtx_4090_tupi5"}
{"kind": "layer", "kernel_size": 2, "in_ch": 32, "out_ch": 32, "batch_size": 8, "input_resolution": 64, "precision": "fp32", "latency_ms": 0.030553340911865234, "winograd_speedup_info": {"speedup_ratio": 1.9179407937540665, "winograd_inferred": true}, "device": "nvidia_geforce_rtx_4090_tupi5"}
{"kind": "layer", "kernel_size": 2, "in_ch": 32, "out_ch": 32, "batch_size": 8, "input_resolution": 64, "precision": "int8", "latency_ms": 0.030611753463745117, "winograd_speedup_info": {"speedup_ratio": 1.9186925766322465, "winograd_inferred": true}, "device": "nvidia_geforce_rtx_4090_tupi5"}
{"kind": "layer", "kernel_size": 2, "in_ch": 32, "out_ch": 32, "batch_size": 8, "input_resolution": 128, "precision": "fp32", "latency_ms": 0.0357973575592041, "winograd_speedup_info": {"speedup_ratio": 3.87148843706348, "winograd_inferred": true}, "device": "nvidia_geforce_rtx_4090_tupi5"}
{"kind": "layer", "kernel_size": 2, "in_ch": 32, "out_ch": 32, "batch_size": 8, "input_resolution": 128, "precision": "int8", "latency_ms": 0.03575444221496582, "winograd_speedup_info": {"speedup_ratio": 3.8728215767634855, "winograd_inferred": true}, "device": "nvidia_geforce_rtx_4090_tupi5"}
{"kind": "layer", "kernel_size": 2, "in_ch": 64, "out_ch": 64, "batch_size": 1, "input_resolution": 64, "precision": "fp32", "latency_ms": 0.03634929656982422, "winograd_speedup_info": {"speedup_ratio": 1.2415966386554622, "winograd_inferred": false}, "device": "nvidia_geforce_rtx_4090_tupi5"}
{"kind": "layer", "kernel_size": 2, "in_ch": 64, "out_ch": 64, "batch_size": 1, "input_resolution": 64, "precision": "int8", "latency_ms": 0.03598213195800781, "winograd_speedup_info": {"speedup_ratio": 1.2555709737980574, "winograd_inferred": false}, "device": "nvidia_geforce_rtx_4090_tupi5"}
{"kind": "layer", "kernel_size": 2, "in_ch": 64, "out_ch": 64, "batch_size": 1, "input_resolution": 128, "precision": "fp32", "latency_ms": 0.03570437431335449, "winograd_speedup_info": {"speedup_ratio": 2.940961507227546, "winograd_inferred": true}, "device": "nvidia_geforce_rtx_4090_tupi5"}
{"kind": "layer", "kernel_size": 2, "in_ch": 64, "out_ch": 64, "batch_size": 1, "input_resolution": 128, "precision": "int8", "latency_ms": 0.035746097564697266, "winograd_speedup_info": {"speedup_ratio": 2.938607903724183, "winograd_inferred": true}, "device": "nvidia_geforce_rtx_4090_tupi5"}
{"kind": "layer", "kernel_size": 2, "in_ch": 64, "out_ch": 64, "batch_size": 8, "input_resolution": 64, "precision": "fp32", "latency_ms": 0.03071427345275879, "winograd_speedup_info": {"speedup_ratio": 2.7583485891042234, "winograd_inferred": true}, "device": "nvidia_geforce_rtx_4090_tupi5"}
{"kind": "layer", "kernel_size": 2, "in_ch": 64, "out_ch": 64, "batch_size": 8, "input_resolution": 64, "precision": "int8", "latency_ms": 0.030504465103149414, "winograd_speedup_info": {"speedup_ratio": 2.7683096806893057, "winograd_inferred": true}, "device": "nvidia_geforce_rtx_4090_tupi5"}
{"kind": "layer", "kernel_size": 2, "in_ch": 64, "out_ch": 64, "batch_size": 8, "input_resolution": 128, "precision": "fp32", "latency_ms": 0.13788461685180664, "winograd_speedup_info": {"speedup_ratio": 3.3012509619342483, "winograd_inferred": true}, "device": "nvidia_geforce_rtx_4090_tupi5"}
{"kind": "layer", "kernel_size": 2, "in_ch": 64, "out_ch": 64, "batch_size": 8, "input_resolution": 128, "precision": "int8", "latency_ms": 0.13750910758972168, "winograd_speedup_info": {"speedup_ratio": 3.272954358919459, "winograd_inferred": true}, "device": "nvidia_geforce_rtx_4090_tupi5"}
{"kind": "layer", "kernel_size": 2, "in_ch": 128, "out_ch": 128, "batch_size": 1, "input_resolution": 64, "precision": "fp32", "latency_ms": 0.036917924880981445, "winograd_speedup_info": {"speedup_ratio": 1.6896860986547084, "winograd_inferred": false}, "device": "nvidia_geforce_rtx_4090_tupi5"}
{"kind": "layer", "kernel_size": 2, "in_ch": 128, "out_ch": 128, "batch_size": 1, "input_resolution": 64, "precision": "int8", "latency_ms": 0.03685474395751953, "winograd_speedup_info": {"speedup_ratio": 1.7075946235672466, "winograd_inferred": false}, "device": "nvidia_geforce_rtx_4090_tupi5"}
{"kind": "layer", "kernel_size": 2, "in_ch": 128, "out_ch": 128, "batch_size": 1, "input_resolution": 128, "precision": "fp32", "latency_ms": 0.039086341857910156, "winograd_speedup_info": {"speedup_ratio": 2.388380159556018, "winograd_inferred": true}, "device": "nvidia_geforce_rtx_4090_tupi5"}
{"kind": "layer", "kernel_size": 2, "in_ch": 128, "out_ch": 128, "batch_size": 1, "input_resolution": 128, "precision": "int8", "latency_ms": 0.03907442092895508, "winograd_speedup_info": {"speedup_ratio": 2.388035373677822, "winograd_inferred": true}, "device": "nvidia_geforce_rtx_4090_tupi5"}
{"kind": "layer", "kernel_size": 2, "in_ch": 128, "out_ch": 128, "batch_size": 8, "input_resolution": 64, "precision": "fp32", "latency_ms": 0.06833314895629883, "winograd_speedup_info": {"speedup_ratio": 3.820971914957441, "winograd_inferred": true}, "device": "nvidia_geforce_rtx_4090_tupi5"}
{"kind": "layer", "kernel_size": 2, "in_ch": 128, "out_ch": 128, "batch_size": 8, "input_resolution": 64, "precision": "int8", "latency_ms": 0.06806373596191406, "winograd_speedup_info": {"speedup_ratio": 3.8426860500150646, "winograd_inferred": true}, "device": "nvidia_geforce_rtx_4090_tupi5"}
{"kind": "layer", "kernel_size": 2, "in_ch": 128, "out_ch": 128, "batch_size": 8, "input_resolution": 128, "precision": "fp32", "latency_ms": 0.37086963653564453, "winograd_speedup_info": {"speedup_ratio": 2.249678800856531, "winograd_inferred": true}, "device": "nvidia_geforce_rtx_4090_tupi5"}
{"kind": "layer", "kernel_size": 2, "in_ch": 128, "out_ch": 128, "batch_size": 8, "input_resolution": 128, "precision": "int8", "latency_ms": 0.371248722076416, "winograd_speedup_info": {"speedup_ratio": 2.2463499321505362, "winograd_inferred": true}, "device": "nvidia_geforce_rtx_4090_tupi5"}
{"kind": "layer", "kernel_size": 3, "in_ch": 16, "out_ch": 16, "batch_size": 1, "input_resolution": 64, "precision": "fp32", "latency_ms": 0.028907060623168945, "winograd_speedup_info": {"speedup_ratio": 1.2655732273028495, "winograd_inferred": false}, "device": "nvidia_geforce_rtx_4090_tupi5"}
{"kind": "layer", "kernel_size": 3, "in_ch": 16, "out_ch": 16, "batch_size": 1, "input_resolution": 64, "precision": "int8", "latency_ms": 0.029206275939941406, "winograd_speedup_info": {"speedup_ratio": 1.2627851437041917, "winograd_inferred": false}, "device": "nvidia_geforce_rtx_4090_tupi5"}
{"kind": "layer", "kernel_size": 3, "in_ch": 16, "out_ch": 16, "batch_size": 1, "input_resolution": 128, "precision": "fp32", "latency_ms": 0.029376745223999023, "winograd_speedup_info": {"speedup_ratio": 1.2405196914332115, "winograd_inferred": false}, "device": "nvidia_geforce_rtx_4090_tupi5"}
{"kind": "layer", "kernel_size": 3, "in_ch": 16, "out_ch": 16, "batch_size": 1, "input_resolution": 128, "precision": "int8", "latency_ms": 0.02922654151916504, "winograd_speedup_info": {"speedup_ratio": 1.255008210180624, "winograd_inferred": false}, "device": "nvidia_geforce_rtx_4090_tupi5"}
{"kind": "layer", "kernel_size": 3, "in_ch": 16, "out_ch": 16, "batch_size": 8, "input_resolution": 64, "precision": "fp32", "latency_ms": 0.02933502197265625, "winograd_speedup_info": {"speedup_ratio": 1.6620050410602487, "winograd_inferred": false}, "device": "nvidia_geforce_rtx_4090_tupi5"}
{"kind": "layer", "kernel_size": 3, "in_ch": 16, "out_ch": 16, "batch_size": 8, "input_resolution": 64, "precision": "int8", "latency_ms": 0.029163360595703125, "winograd_speedup_info": {"speedup_ratio": 1.666884176182708, "winograd_inferred": false}, "device": "nvidia_geforce_rtx_4090_tupi5"}
{"kind": "layer", "kernel_size": 3, "in_ch": 16, "out_ch": 16, "batch_size": 8, "input_resolution": 128, "precision": "fp32", "latency_ms": 0.029151439666748047, "winograd_speedup_info": {"speedup_ratio": 2.2049669408159973, "winograd_inferred": true}, "device": "nvidia_geforce_rtx_4090_tupi5"}
{"kind": "layer", "kernel_size": 3, "in_ch": 16, "out_ch": 16, "batch_size": 8, "input_resolution": 128, "precision": "int8", "latency_ms": 0.02918839454650879, "winograd_speedup_info": {"speedup_ratio": 2.2148166101147195, "winograd_inferred": true}, "device": "nvidia_geforce_rtx_4090_tupi5"}
{"kind": "layer", "kernel_size": 3, "in_ch": 32, "out_ch": 32, "batch_size": 1, "input_resolution": 64, "precision": "fp32", "latency_ms": 0.029137134552001953, "winograd_speedup_info": {"speedup_ratio": 1.2735112268141882, "winograd_inferred": false}, "device": "nvidia_geforce_rtx_4090_tupi5"}
{"kind": "layer", "kernel_size": 3, "in_ch": 32, "out_ch": 32, "batch_size": 1, "input_resolution": 64, "precision": "int8", "latency_ms": 0.02907872200012207, "winograd_speedup_info": {"speedup_ratio": 1.269972904179325, "winograd_inferred": false}, "device": "nvidia_geforce_rtx_4090_tupi5"}
{"kind": "layer", "kernel_size": 3, "in_ch": 32, "out_ch": 32, "batch_size": 1, "input_resolution": 128, "precision": "fp32", "latency_ms": 0.029098987579345703, "winograd_speedup_info": {"speedup_ratio": 1.229653047989624, "winograd_inferred": false}, "device": "nvidia_geforce_rtx_4090_tupi5"}
{"kind": "layer", "kernel_size": 3, "in_ch": 32, "out_ch": 32, "batch_size": 1, "input_resolution": 128, "precision": "int8", "latency_ms": 0.02928614616394043, "winograd_speedup_info": {"speedup_ratio": 1.227939977165226, "winograd_inferred": false}, "device": "nvidia_geforce_rtx_4090_tupi5"}
{"kind": "layer", "kernel_size": 3, "in_ch": 32, "out_ch": 32, "batch_size": 8, "input_resolution": 64, "precision": "fp32", "latency_ms": 0.029288530349731445, "winograd_speedup_info": {"speedup_ratio": 1.8146301593788312, "winograd_inferred": true}, "device": "nvidia_geforce_rtx_4090_tupi5"}
{"kind": "layer", "kernel_size": 3, "in_ch": 32, "out_ch": 32, "batch_size": 8, "input_resolution": 64, "precision": "int8", "latency_ms": 0.029314756393432617, "winograd_speedup_info": {"speedup_ratio": 1.78921885087153, "winograd_inferred": false}, "device": "nvidia_geforce_rtx_4090_tupi5"}
{"kind": "layer", "kernel_size": 3, "in_ch": 32, "out_ch": 32, "batch_size": 8, "input_resolution": 128, "precision": "fp32", "latency_ms": 0.043119192123413086, "winograd_speedup_info": {"speedup_ratio": 3.935210181257231, "winograd_inferred": true}, "device": "nvidia_geforce_rtx_4090_tupi5"}
{"kind": "layer", "kernel_size": 3, "in_ch": 32, "out_ch": 32, "batch_size": 8, "input_resolution": 128, "precision": "int8", "latency_ms": 0.043714046478271484, "winograd_speedup_info": {"speedup_ratio": 3.8766076728591843, "winograd_inferred": true}, "device": "nvidia_geforce_rtx_4090_tupi5"}
{"kind": "layer", "kernel_size": 3, "in_ch": 64, "out_ch": 64, "batch_size": 1, "input_resolution": 64, "precision": "fp32", "latency_ms": 0.02920985221862793, "winograd_speedup_info": {"speedup_ratio": 1.2583414318108195, "winograd_inferred": false}, "device": "nvidia_geforce_rtx_4090_tupi5"}
{"kind": "layer", "kernel_size": 3, "in_ch": 64, "out_ch": 64, "batch_size": 1, "input_resolution": 64, "precision": "int8", "latency_ms": 0.029420852661132812, "winograd_speedup_info": {"speedup_ratio": 1.264571800716379, "winograd_inferred": false}, "device": "nvidia_geforce_rtx_4090_tupi5"}
{"kind": "layer", "kernel_size": 3, "in_ch": 64, "out_ch": 64, "batch_size": 1, "input_resolution": 128, "precision": "fp32", "latency_ms": 0.02939462661743164, "winograd_speedup_info": {"speedup_ratio": 2.945967938807063, "winograd_inferred": true}, "device": "nvidia_geforce_rtx_4090_tupi5"}
{"kind": "layer", "kernel_size": 3, "in_ch": 64, "out_ch": 64, "batch_size": 1, "input_resolution": 128, "precision": "int8", "latency_ms": 0.029282569885253906, "winograd_speedup_info": {"speedup_ratio": 2.9248967025844608, "winograd_inferred": true}, "device": "nvidia_geforce_rtx_4090_tupi5"}
{"kind": "layer", "kernel_size": 3, "in_ch": 64, "out_ch": 64, "batch_size": 8, "input_resolution": 64, "precision": "fp32", "latency_ms": 0.037593841552734375, "winograd_speedup_info": {"speedup_ratio": 2.766934412750617, "winograd_inferred": true}, "device": "nvidia_geforce_rtx_4090_tupi5"}
{"kind": "layer", "kernel_size": 3, "in_ch": 64, "out_ch": 64, "batch_size": 8, "input_resolution": 64, "precision": "int8", "latency_ms": 0.037631988525390625, "winograd_speedup_info": {"speedup_ratio": 2.7650926101523483, "winograd_inferred": true}, "device": "nvidia_geforce_rtx_4090_tupi5"}
{"kind": "layer", "kernel_size": 3, "in_ch": 64, "out_ch": 64, "batch_size": 8, "input_resolution": 128, "precision": "fp32", "latency_ms": 0.13367891311645508, "winograd_speedup_info": {"speedup_ratio": 3.3874727649549183, "winograd_inferred": true}, "device": "nvidia_geforce_rtx_4090_tupi5"}
{"kind": "layer", "kernel_size": 3, "in_ch": 64, "out_ch": 64, "batch_size": 8, "input_resolution": 128, "precision": "int8", "latency_ms": 0.13637065887451172, "winograd_speedup_info": {"speedup_ratio": 3.2324173581825604, "winograd_inferred": true}, "device": "nvidia_geforce_rtx_4090_tupi5"}
{"kind": "layer", "kernel_size": 3, "in_ch": 128, "out_ch": 128, "batch_size": 1, "input_resolution": 64, "precision": "fp32", "latency_ms": 0.02926945686340332, "winograd_speedup_info": {"speedup_ratio": 1.7129111842105262, "winograd_inferred": false}, "device": "nvidia_geforce_rtx_4090_tupi5"}
{"kind": "layer", "kernel_size": 3, "in_ch": 128, "out_ch": 128, "batch_size": 1, "input_resolution": 64, "precision": "int8", "latency_ms": 0.029047727584838867, "winograd_speedup_info": {"speedup_ratio": 1.7093665046544197, "winograd_inferred": false}, "device": "nvidia_geforce_rtx_4090_tupi5"}
{"kind": "layer", "kernel_size": 3, "in_ch": 128, "out_ch": 128, "batch_size": 1, "input_resolution": 128, "precision": "fp32", "latency_ms": 0.06884932518005371, "winograd_speedup_info": {"speedup_ratio": 2.389029069164564, "winograd_inferred": true}, "device": "nvidia_geforce_rtx_4090_tupi5"}
{"kind": "layer", "kernel_size": 3, "in_ch": 128, "out_ch": 128, "batch_size": 1, "input_resolution": 128, "precision": "int8", "latency_ms": 0.06885886192321777, "winograd_speedup_info": {"speedup_ratio": 2.3876986869384935, "winograd_inferred": true}, "device": "nvidia_geforce_rtx_4090_tupi5"}
{"kind": "layer", "kernel_size": 3, "in_ch": 128, "out_ch": 128, "batch_size": 8, "input_resolution": 64, "precision": "fp32", "latency_ms": 0.12736797332763672, "winograd_speedup_info": {"speedup_ratio": 3.8250397381954184, "winograd_inferred": true}, "device": "nvidia_geforce_rtx_4090_tupi5"}
{"kind": "layer", "kernel_size": 3, "in_ch": 128, "out_ch": 128, "batch_size": 8, "input_resolution": 64, "precision": "int8", "latency_ms": 0.12729525566101074, "winograd_speedup_info": {"speedup_ratio": 3.825715354404339, "winograd_inferred": true}, "device": "nvidia_geforce_rtx_4090_tupi5"}
{"kind": "layer", "kernel_size": 3, "in_ch": 128, "out_ch": 128, "batch_size": 8, "input_resolution": 128, "precision": "fp32", "latency_ms": 0.6147193908691406, "winograd_speedup_info": {"speedup_ratio": 2.24692057089668, "winograd_inferred": true}, "device": "nvidia_geforce_rtx_4090_tupi5"}
{"kind": "layer", "kernel_size": 3, "in_ch": 128, "out_ch": 128, "batch_size": 8, "input_resolution": 128, "precision": "int8", "latency_ms": 0.6149756908416748, "winograd_speedup_info": {"speedup_ratio": 2.24624539639465, "winograd_inferred": true}, "device": "nvidia_geforce_rtx_4090_tupi5"}
{"kind": "layer", "kernel_size": 5, "in_ch": 16, "out_ch": 16, "batch_size": 1, "input_resolution": 64, "precision": "fp32", "latency_ms": 0.03663897514343262, "winograd_speedup_info": {"speedup_ratio": 1.2694309077393244, "winograd_inferred": false}, "device": "nvidia_geforce_rtx_4090_tupi5"}
{"kind": "layer", "kernel_size": 5, "in_ch": 16, "out_ch": 16, "batch_size": 1, "input_resolution": 64, "precision": "int8", "latency_ms": 0.036607980728149414, "winograd_speedup_info": {"speedup_ratio": 1.267996028462684, "winograd_inferred": false}, "device": "nvidia_geforce_rtx_4090_tupi5"}
{"kind": "layer", "kernel_size": 5, "in_ch": 16, "out_ch": 16, "batch_size": 1, "input_resolution": 128, "precision": "fp32", "latency_ms": 0.03567695617675781, "winograd_speedup_info": {"speedup_ratio": 1.2409827928524155, "winograd_inferred": false}, "device": "nvidia_geforce_rtx_4090_tupi5"}
{"kind": "layer", "kernel_size": 5, "in_ch": 16, "out_ch": 16, "batch_size": 1, "input_resolution": 128, "precision": "int8", "latency_ms": 0.03562808036804199, "winograd_speedup_info": {"speedup_ratio": 1.2329037024874805, "winograd_inferred": false}, "device": "nvidia_geforce_rtx_4090_tupi5"}
{"kind": "layer", "kernel_size": 5, "in_ch": 16, "out_ch": 16, "batch_size": 8, "input_resolution": 64, "precision": "fp32", "latency_ms": 0.048584938049316406, "winograd_speedup_info": {"speedup_ratio": 1.687345322554034, "winograd_inferred": false}, "device": "nvidia_geforce_rtx_4090_tupi5"}
{"kind": "layer", "kernel_size": 5, "in_ch": 16, "out_ch": 16, "batch_size": 8, "input_resolution": 64, "precision": "int8", "latency_ms": 0.04860043525695801, "winograd_speedup_info": {"speedup_ratio": 1.6801150369761708, "winograd_inferred": false}, "device": "nvidia_geforce_rtx_4090_tupi5"}
{"kind": "layer", "kernel_size": 5, "in_ch": 16, "out_ch": 16, "batch_size": 8, "input_resolution": 128, "precision": "fp32", "latency_ms": 0.06514191627502441, "winograd_speedup_info": {"speedup_ratio": 2.2293600390815826, "winograd_inferred": true}, "device": "nvidia_geforce_rtx_4090_tupi5"}
{"kind": "layer", "kernel_size": 5, "in_ch": 16, "out_ch": 16, "batch_size": 8, "input_resolution": 128, "precision": "int8", "latency_ms": 0.06515264511108398, "winograd_speedup_info": {"speedup_ratio": 2.230612577386771, "winograd_inferred": true}, "device": "nvidia_geforce_rtx_4090_tupi5"}
{"kind": "layer", "kernel_size": 5, "in_ch": 32, "out_ch": 32, "batch_size": 1, "input_resolution": 64, "precision": "fp32", "latency_ms": 0.036519765853881836, "winograd_speedup_info": {"speedup_ratio": 1.2613514184103878, "winograd_inferred": false}, "device": "nvidia_geforce_rtx_4090_tupi5"}
{"kind": "layer", "kernel_size": 5, "in_ch": 32, "out_ch": 32, "batch_size": 1, "input_resolution": 64, "precision": "int8", "latency_ms": 0.03673195838928223, "winograd_speedup_info": {"speedup_ratio": 1.2584251325989393, "winograd_inferred": false}, "device": "nvidia_geforce_rtx_4090_tupi5"}
{"kind": "layer", "kernel_size": 5, "in_ch": 32, "out_ch": 32, "batch_size": 1, "input_resolution": 128, "precision": "fp32", "latency_ms": 0.03573775291442871, "winograd_speedup_info": {"speedup_ratio": 1.2315339742009694, "winograd_inferred": false}, "device": "nvidia_geforce_rtx_4090_tupi5"}
{"kind": "layer", "kernel_size": 5, "in_ch": 32, "out_ch": 32, "batch_size": 1, "input_resolution": 128, "precision": "int8", "latency_ms": 0.03560185432434082, "winograd_speedup_info": {"speedup_ratio": 1.2314906219151036, "winograd_inferred": false}, "device": "nvidia_geforce_rtx_4090_tupi5"}
{"kind": "layer", "kernel_size": 5, "in_ch": 32, "out_ch": 32, "batch_size": 8, "input_resolution": 64, "precision": "fp32", "latency_ms": 0.05268573760986328, "winograd_speedup_info": {"speedup_ratio": 1.8307438016528925, "winograd_inferred": true}, "device": "nvidia_geforce_rtx_4090_tupi5"}
{"kind": "layer", "kernel_size": 5, "in_ch": 32, "out_ch": 32, "batch_size": 8, "input_resolution": 64, "precision": "int8", "latency_ms": 0.05268454551696777, "winograd_speedup_info": {"speedup_ratio": 1.8249958861280238, "winograd_inferred": true}, "device": "nvidia_geforce_rtx_4090_tupi5"}
{"kind": "layer", "kernel_size": 5, "in_ch": 32, "out_ch": 32, "batch_size": 8, "input_resolution": 128, "precision": "fp32", "latency_ms": 0.1705777645111084, "winograd_speedup_info": {"speedup_ratio": 3.8697242841993638, "winograd_inferred": true}, "device": "nvidia_geforce_rtx_4090_tupi5"}
{"kind": "layer", "kernel_size": 5, "in_ch": 32, "out_ch": 32, "batch_size": 8, "input_resolution": 128, "precision": "int8", "latency_ms": 0.1707780361175537, "winograd_speedup_info": {"speedup_ratio": 3.9402091047702026, "winograd_inferred": true}, "device": "nvidia_geforce_rtx_4090_tupi5"}
{"kind": "layer", "kernel_size": 5, "in_ch": 64, "out_ch": 64, "batch_size": 1, "input_resolution": 64, "precision": "fp32", "latency_ms": 0.03689289093017578, "winograd_speedup_info": {"speedup_ratio": 1.2642482803799542, "winograd_inferred": false}, "device": "nvidia_geforce_rtx_4090_tupi5"}
{"kind": "layer", "kernel_size": 5, "in_ch": 64, "out_ch": 64, "batch_size": 1, "input_resolution": 64, "precision": "int8", "latency_ms": 0.03637194633483887, "winograd_speedup_info": {"speedup_ratio": 1.255655737704918, "winograd_inferred": false}, "device": "nvidia_geforce_rtx_4090_tupi5"}
{"kind": "layer", "kernel_size": 5, "in_ch": 64, "out_ch": 64, "batch_size": 1, "input_resolution": 128, "precision": "fp32", "latency_ms": 0.0863957405090332, "winograd_speedup_info": {"speedup_ratio": 2.9774349716911463, "winograd_inferred": true}, "device": "nvidia_geforce_rtx_4090_tupi5"}
{"kind": "layer", "kernel_size": 5, "in_ch": 64, "out_ch": 64, "batch_size": 1, "input_resolution": 128, "precision": "int8", "latency_ms": 0.08593440055847168, "winograd_speedup_info": {"speedup_ratio": 2.95039633897197, "winograd_inferred": true}, "device": "nvidia_geforce_rtx_4090_tupi5"}
{"kind": "layer", "kernel_size": 5, "in_ch": 64, "out_ch": 64, "batch_size": 8, "input_resolution": 64, "precision": "fp32", "latency_ms": 0.10412812232971191, "winograd_speedup_info": {"speedup_ratio": 2.761008275949207, "winograd_inferred": true}, "device": "nvidia_geforce_rtx_4090_tupi5"}
{"kind": "layer", "kernel_size": 5, "in_ch": 64, "out_ch": 64, "batch_size": 8, "input_resolution": 64, "precision": "int8", "latency_ms": 0.10408163070678711, "winograd_speedup_info": {"speedup_ratio": 2.7595304216107044, "winograd_inferred": true}, "device": "nvidia_geforce_rtx_4090_tupi5"}
{"kind": "layer", "kernel_size": 5, "in_ch": 64, "out_ch": 64, "batch_size": 8, "input_resolution": 128, "precision": "fp32", "latency_ms": 0.4371309280395508, "winograd_speedup_info": {"speedup_ratio": 3.323336774285409, "winograd_inferred": true}, "device": "nvidia_geforce_rtx_4090_tupi5"}
{"kind": "layer", "kernel_size": 5, "in_ch": 64, "out_ch": 64, "batch_size": 8, "input_resolution": 128, "precision": "int8", "latency_ms": 0.4388272762298584, "winograd_speedup_info": {"speedup_ratio": 3.358323714818432, "winograd_inferred": true}, "device": "nvidia_geforce_rtx_4090_tupi5"}
{"kind": "layer", "kernel_size": 5, "in_ch": 128, "out_ch": 128, "batch_size": 1, "input_resolution": 64, "precision": "fp32", "latency_ms": 0.04941105842590332, "winograd_speedup_info": {"speedup_ratio": 1.6937927663734116, "winograd_inferred": false}, "device": "nvidia_geforce_rtx_4090_tupi5"}
{"kind": "layer", "kernel_size": 5, "in_ch": 128, "out_ch": 128, "batch_size": 1, "input_resolution": 64, "precision": "int8", "latency_ms": 0.04945039749145508, "winograd_speedup_info": {"speedup_ratio": 1.7028398395940747, "winograd_inferred": false}, "device": "nvidia_geforce_rtx_4090_tupi5"}
{"kind": "layer", "kernel_size": 5, "in_ch": 128, "out_ch": 128, "batch_size": 1, "input_resolution": 128, "precision": "fp32", "latency_ms": 0.16457080841064453, "winograd_speedup_info": {"speedup_ratio": 2.386552879798224, "winograd_inferred": true}, "device": "nvidia_geforce_rtx_4090_tupi5"}
{"kind": "layer", "kernel_size": 5, "in_ch": 128, "out_ch": 128, "batch_size": 1, "input_resolution": 128, "precision": "int8", "latency_ms": 0.16315460205078125, "winograd_speedup_info": {"speedup_ratio": 2.385518250208972, "winograd_inferred": true}, "device": "nvidia_geforce_rtx_4090_tupi5"}
{"kind": "layer", "kernel_size": 5, "in_ch": 128, "out_ch": 128, "batch_size": 8, "input_resolution": 64, "precision": "fp32", "latency_ms": 0.48674941062927246, "winograd_speedup_info": {"speedup_ratio": 3.8380496054114994, "winograd_inferred": true}, "device": "nvidia_geforce_rtx_4090_tupi5"}
{"kind": "layer", "kernel_size": 5, "in_ch": 128, "out_ch": 128, "batch_size": 8, "input_resolution": 64, "precision": "int8", "latency_ms": 0.48682093620300293, "winograd_speedup_info": {"speedup_ratio": 3.8379109524704114, "winograd_inferred": true}, "device": "nvidia_geforce_rtx_4090_tupi5"}
{"kind": "layer", "kernel_size": 5, "in_ch": 128, "out_ch": 128, "batch_size": 8, "input_resolution": 128, "precision": "fp32", "latency_ms": 1.3789665699005127, "winograd_speedup_info": {"speedup_ratio": 2.2458927295878754, "winograd_inferred": true}, "device": "nvidia_geforce_rtx_4090_tupi5"}
{"kind": "layer", "kernel_size": 5, "in_ch": 128, "out_ch": 128, "batch_size": 8, "input_resolution": 128, "precision": "int8", "latency_ms": 1.3795363903045654, "winograd_speedup_info": {"speedup_ratio": 2.245378796993065, "winograd_inferred": true}, "device": "nvidia_geforce_rtx_4090_tupi5"}
{"kind": "layer", "kernel_size": 7, "in_ch": 16, "out_ch": 16, "batch_size": 1, "input_resolution": 64, "precision": "fp32", "latency_ms": 0.03630518913269043, "winograd_speedup_info": {"speedup_ratio": 1.272576910353953, "winograd_inferred": false}, "device": "nvidia_geforce_rtx_4090_tupi5"}
{"kind": "layer", "kernel_size": 7, "in_ch": 16, "out_ch": 16, "batch_size": 1, "input_resolution": 64, "precision": "int8", "latency_ms": 0.03618597984313965, "winograd_speedup_info": {"speedup_ratio": 1.2733609958506225, "winograd_inferred": false}, "device": "nvidia_geforce_rtx_4090_tupi5"}
{"kind": "layer", "kernel_size": 7, "in_ch": 16, "out_ch": 16, "batch_size": 1, "input_resolution": 128, "precision": "fp32", "latency_ms": 0.0451815128326416, "winograd_speedup_info": {"speedup_ratio": 1.261916461916462, "winograd_inferred": false}, "device": "nvidia_geforce_rtx_4090_tupi5"}
{"kind": "layer", "kernel_size": 7, "in_ch": 16, "out_ch": 16, "batch_size": 1, "input_resolution": 128, "precision": "int8", "latency_ms": 0.04505753517150879, "winograd_speedup_info": {"speedup_ratio": 1.2545334652159579, "winograd_inferred": false}, "device": "nvidia_geforce_rtx_4090_tupi5"}
{"kind": "layer", "kernel_size": 7, "in_ch": 16, "out_ch": 16, "batch_size": 8, "input_resolution": 64, "precision": "fp32", "latency_ms": 0.08512377738952637, "winograd_speedup_info": {"speedup_ratio": 1.6789728443678726, "winograd_inferred": false}, "device": "nvidia_geforce_rtx_4090_tupi5"}
{"kind": "layer", "kernel_size": 7, "in_ch": 16, "out_ch": 16, "batch_size": 8, "input_resolution": 64, "precision": "int8", "latency_ms": 0.08512139320373535, "winograd_speedup_info": {"speedup_ratio": 1.6904781567429186, "winograd_inferred": false}, "device": "nvidia_geforce_rtx_4090_tupi5"}
{"kind": "layer", "kernel_size": 7, "in_ch": 16, "out_ch": 16, "batch_size": 8, "input_resolution": 128, "precision": "fp32", "latency_ms": 0.3768277168273926, "winograd_speedup_info": {"speedup_ratio": 2.2291904218928162, "winograd_inferred": true}, "device": "nvidia_geforce_rtx_4090_tupi5"}
{"kind": "layer", "kernel_size": 7, "in_ch": 16, "out_ch": 16, "batch_size": 8, "input_resolution": 128, "precision": "int8", "latency_ms": 0.377277135848999, "winograd_speedup_info": {"speedup_ratio": 2.2296857189382835, "winograd_inferred": true}, "device": "nvidia_geforce_rtx_4090_tupi5"}
{"kind": "layer", "kernel_size": 7, "in_ch": 32, "out_ch": 32, "batch_size": 1, "input_resolution": 64, "precision": "fp32", "latency_ms": 0.036896467208862305, "winograd_speedup_info": {"speedup_ratio": 1.2538386148317544, "winograd_inferred": false}, "device": "nvidia_geforce_rtx_4090_tupi5"}
{"kind": "layer", "kernel_size": 7, "in_ch": 32, "out_ch": 32, "batch_size": 1, "input_resolution": 64, "precision": "int8", "latency_ms": 0.03689408302307129, "winograd_speedup_info": {"speedup_ratio": 1.274929717215148, "winograd_inferred": false}, "device": "nvidia_geforce_rtx_4090_tupi5"}
{"kind": "layer", "kernel_size": 7, "in_ch": 32, "out_ch": 32, "batch_size": 1, "input_resolution": 128, "precision": "fp32", "latency_ms": 0.05009174346923828, "winograd_speedup_info": {"speedup_ratio": 1.225885225885226, "winograd_inferred": false}, "device": "nvidia_geforce_rtx_4090_tupi5"}
{"kind": "layer", "kernel_size": 7, "in_ch": 32, "out_ch": 32, "batch_size": 1, "input_resolution": 128, "precision": "int8", "latency_ms": 0.05005240440368652, "winograd_speedup_info": {"speedup_ratio": 1.2306372549019609, "winograd_inferred": false}, "device": "nvidia_geforce_rtx_4090_tupi5"}
{"kind": "layer", "kernel_size": 7, "in_ch": 32, "out_ch": 32, "batch_size": 8, "input_resolution": 64, "precision": "fp32", "latency_ms": 0.09257197380065918, "winograd_speedup_info": {"speedup_ratio": 1.8196371398078977, "winograd_inferred": true}, "device": "nvidia_geforce_rtx_4090_tupi5"}
{"kind": "layer", "kernel_size": 7, "in_ch": 32, "out_ch": 32, "batch_size": 8, "input_resolution": 64, "precision": "int8", "latency_ms": 0.09259581565856934, "winograd_speedup_info": {"speedup_ratio": 1.808451623429597, "winograd_inferred": true}, "device": "nvidia_geforce_rtx_4090_tupi5"}
{"kind": "layer", "kernel_size": 7, "in_ch": 32, "out_ch": 32, "batch_size": 8, "input_resolution": 128, "precision": "fp32", "latency_ms": 0.34587621688842773, "winograd_speedup_info": {"speedup_ratio": 3.876247725142006, "winograd_inferred": true}, "device": "nvidia_geforce_rtx_4090_tupi5"}
{"kind": "layer", "kernel_size": 7, "in_ch": 32, "out_ch": 32, "batch_size": 8, "input_resolution": 128, "precision": "int8", "latency_ms": 0.3464508056640625, "winograd_speedup_info": {"speedup_ratio": 3.8917565485362093, "winograd_inferred": true}, "device": "nvidia_geforce_rtx_4090_tupi5"}
{"kind": "layer", "kernel_size": 7, "in_ch": 64, "out_ch": 64, "batch_size": 1, "input_resolution": 64, "precision": "fp32", "latency_ms": 0.039467811584472656, "winograd_speedup_info": {"speedup_ratio": 1.2754063372188476, "winograd_inferred": false}, "device": "nvidia_geforce_rtx_4090_tupi5"}
{"kind": "layer", "kernel_size": 7, "in_ch": 64, "out_ch": 64, "batch_size": 1, "input_resolution": 64, "precision": "int8", "latency_ms": 0.03882169723510742, "winograd_speedup_info": {"speedup_ratio": 1.262151067323481, "winograd_inferred": false}, "device": "nvidia_geforce_rtx_4090_tupi5"}
{"kind": "layer", "kernel_size": 7, "in_ch": 64, "out_ch": 64, "batch_size": 1, "input_resolution": 128, "precision": "fp32", "latency_ms": 0.0854194164276123, "winograd_speedup_info": {"speedup_ratio": 2.9334196262438312, "winograd_inferred": true}, "device": "nvidia_geforce_rtx_4090_tupi5"}
{"kind": "layer", "kernel_size": 7, "in_ch": 64, "out_ch": 64, "batch_size": 1, "input_resolution": 128, "precision": "int8", "latency_ms": 0.08536577224731445, "winograd_speedup_info": {"speedup_ratio": 2.9662930540783767, "winograd_inferred": true}, "device": "nvidia_geforce_rtx_4090_tupi5"}
{"kind": "layer", "kernel_size": 7, "in_ch": 64, "out_ch": 64, "batch_size": 8, "input_resolution": 64, "precision": "fp32", "latency_ms": 0.44312477111816406, "winograd_speedup_info": {"speedup_ratio": 2.7684887459807075, "winograd_inferred": true}, "device": "nvidia_geforce_rtx_4090_tupi5"}
{"kind": "layer", "kernel_size": 7, "in_ch": 64, "out_ch": 64, "batch_size": 8, "input_resolution": 64, "precision": "int8", "latency_ms": 0.4430043697357178, "winograd_speedup_info": {"speedup_ratio": 2.7680383136933644, "winograd_inferred": true}, "device": "nvidia_geforce_rtx_4090_tupi5"}
{"kind": "layer", "kernel_size": 7, "in_ch": 64, "out_ch": 64, "batch_size": 8, "input_resolution": 128, "precision": "fp32", "latency_ms": 1.7699062824249268, "winograd_speedup_info": {"speedup_ratio": 3.381871190034455, "winograd_inferred": true}, "device": "nvidia_geforce_rtx_4090_tupi5"}
{"kind": "layer", "kernel_size": 7, "in_ch": 64, "out_ch": 64, "batch_size": 8, "input_resolution": 128, "precision": "int8", "latency_ms": 1.7696142196655273, "winograd_speedup_info": {"speedup_ratio": 3.2787744620561408, "winograd_inferred": true}, "device": "nvidia_geforce_rtx_4090_tupi5"}
{"kind": "layer", "kernel_size": 7, "in_ch": 128, "out_ch": 128, "batch_size": 1, "input_resolution": 64, "precision": "fp32", "latency_ms": 0.08690118789672852, "winograd_speedup_info": {"speedup_ratio": 1.6937627395026498, "winograd_inferred": false}, "device": "nvidia_geforce_rtx_4090_tupi5"}
{"kind": "layer", "kernel_size": 7, "in_ch": 128, "out_ch": 128, "batch_size": 1, "input_resolution": 64, "precision": "int8", "latency_ms": 0.08694887161254883, "winograd_speedup_info": {"speedup_ratio": 1.694981640146879, "winograd_inferred": false}, "device": "nvidia_geforce_rtx_4090_tupi5"}
{"kind": "layer", "kernel_size": 7, "in_ch": 128, "out_ch": 128, "batch_size": 1, "input_resolution": 128, "precision": "fp32", "latency_ms": 0.3170311450958252, "winograd_speedup_info": {"speedup_ratio": 2.3888234886780695, "winograd_inferred": true}, "device": "nvidia_geforce_rtx_4090_tupi5"}
{"kind": "layer", "kernel_size": 7, "in_ch": 128, "out_ch": 128, "batch_size": 1, "input_resolution": 128, "precision": "int8", "latency_ms": 0.31702637672424316, "winograd_speedup_info": {"speedup_ratio": 2.3897700512536364, "winograd_inferred": true}, "device": "nvidia_geforce_rtx_4090_tupi5"}
{"kind": "layer", "kernel_size": 7, "in_ch": 128, "out_ch": 128, "batch_size": 8, "input_resolution": 64, "precision": "fp32", "latency_ms": 0.6250655651092529, "winograd_speedup_info": {"speedup_ratio": 3.833180224601136, "winograd_inferred": true}, "device": "nvidia_geforce_rtx_4090_tupi5"}
{"kind": "layer", "kernel_size": 7, "in_ch": 128, "out_ch": 128, "batch_size": 8, "input_resolution": 64, "precision": "int8", "latency_ms": 0.6259810924530029, "winograd_speedup_info": {"speedup_ratio": 3.833252099580084, "winograd_inferred": true}, "device": "nvidia_geforce_rtx_4090_tupi5"}
{"kind": "layer", "kernel_size": 7, "in_ch": 128, "out_ch": 128, "batch_size": 8, "input_resolution": 128, "precision": "fp32", "latency_ms": 2.591928243637085, "winograd_speedup_info": {"speedup_ratio": 2.2466261336812026, "winograd_inferred": true}, "device": "nvidia_geforce_rtx_4090_tupi5"}
{"kind": "layer", "kernel_size": 7, "in_ch": 128, "out_ch": 128, "batch_size": 8, "input_resolution": 128, "precision": "int8", "latency_ms": 2.592287063598633, "winograd_speedup_info": {"speedup_ratio": 2.2454839323065223, "winograd_inferred": true}, "device": "nvidia_geforce_rtx_4090_tupi5"}
{"kind": "layer", "kernel_size": 9, "in_ch": 16, "out_ch": 16, "batch_size": 1, "input_resolution": 64, "precision": "fp32", "latency_ms": 0.044542551040649414, "winograd_speedup_info": {"speedup_ratio": 1.2609018217789136, "winograd_inferred": false}, "device": "nvidia_geforce_rtx_4090_tupi5"}
{"kind": "layer", "kernel_size": 9, "in_ch": 16, "out_ch": 16, "batch_size": 1, "input_resolution": 64, "precision": "int8", "latency_ms": 0.04450798034667969, "winograd_speedup_info": {"speedup_ratio": 1.2694412203614658, "winograd_inferred": false}, "device": "nvidia_geforce_rtx_4090_tupi5"}
{"kind": "layer", "kernel_size": 9, "in_ch": 16, "out_ch": 16, "batch_size": 1, "input_resolution": 128, "precision": "fp32", "latency_ms": 0.15707850456237793, "winograd_speedup_info": {"speedup_ratio": 1.2450358408173354, "winograd_inferred": false}, "device": "nvidia_geforce_rtx_4090_tupi5"}
{"kind": "layer", "kernel_size": 9, "in_ch": 16, "out_ch": 16, "batch_size": 1, "input_resolution": 128, "precision": "int8", "latency_ms": 0.15700340270996094, "winograd_speedup_info": {"speedup_ratio": 1.2441534914361, "winograd_inferred": false}, "device": "nvidia_geforce_rtx_4090_tupi5"}
{"kind": "layer", "kernel_size": 9, "in_ch": 16, "out_ch": 16, "batch_size": 8, "input_resolution": 64, "precision": "fp32", "latency_ms": 0.13949871063232422, "winograd_speedup_info": {"speedup_ratio": 1.6887586662264773, "winograd_inferred": false}, "device": "nvidia_geforce_rtx_4090_tupi5"}
{"kind": "layer", "kernel_size": 9, "in_ch": 16, "out_ch": 16, "batch_size": 8, "input_resolution": 64, "precision": "int8", "latency_ms": 0.13953328132629395, "winograd_speedup_info": {"speedup_ratio": 1.688056746948202, "winograd_inferred": false}, "device": "nvidia_geforce_rtx_4090_tupi5"}
{"kind": "layer", "kernel_size": 9, "in_ch": 16, "out_ch": 16, "batch_size": 8, "input_resolution": 128, "precision": "fp32", "latency_ms": 0.5382800102233887, "winograd_speedup_info": {"speedup_ratio": 2.226307654762873, "winograd_inferred": true}, "device": "nvidia_geforce_rtx_4090_tupi5"}
{"kind": "layer", "kernel_size": 9, "in_ch": 16, "out_ch": 16, "batch_size": 8, "input_resolution": 128, "precision": "int8", "latency_ms": 0.5379629135131836, "winograd_speedup_info": {"speedup_ratio": 2.230556234221028, "winograd_inferred": true}, "device": "nvidia_geforce_rtx_4090_tupi5"}
{"kind": "layer", "kernel_size": 9, "in_ch": 32, "out_ch": 32, "batch_size": 1, "input_resolution": 64, "precision": "fp32", "latency_ms": 0.03934502601623535, "winograd_speedup_info": {"speedup_ratio": 1.2585981002292828, "winograd_inferred": false}, "device": "nvidia_geforce_rtx_4090_tupi5"}
{"kind": "layer", "kernel_size": 9, "in_ch": 32, "out_ch": 32, "batch_size": 1, "input_resolution": 64, "precision": "int8", "latency_ms": 0.03936171531677246, "winograd_speedup_info": {"speedup_ratio": 1.262797790783942, "winograd_inferred": false}, "device": "nvidia_geforce_rtx_4090_tupi5"}
{"kind": "layer", "kernel_size": 9, "in_ch": 32, "out_ch": 32, "batch_size": 1, "input_resolution": 128, "precision": "fp32", "latency_ms": 0.07417440414428711, "winograd_speedup_info": {"speedup_ratio": 1.2233411841143507, "winograd_inferred": false}, "device": "nvidia_geforce_rtx_4090_tupi5"}
{"kind": "layer", "kernel_size": 9, "in_ch": 32, "out_ch": 32, "batch_size": 1, "input_resolution": 128, "precision": "int8", "latency_ms": 0.07411956787109375, "winograd_speedup_info": {"speedup_ratio": 1.2286550658643682, "winograd_inferred": false}, "device": "nvidia_geforce_rtx_4090_tupi5"}
{"kind": "layer", "kernel_size": 9, "in_ch": 32, "out_ch": 32, "batch_size": 8, "input_resolution": 64, "precision": "fp32", "latency_ms": 0.1411294937133789, "winograd_speedup_info": {"speedup_ratio": 1.8155610155610156, "winograd_inferred": true}, "device": "nvidia_geforce_rtx_4090_tupi5"}
{"kind": "layer", "kernel_size": 9, "in_ch": 32, "out_ch": 32, "batch_size": 8, "input_resolution": 64, "precision": "int8", "latency_ms": 0.14126896858215332, "winograd_speedup_info": {"speedup_ratio": 1.8274441973478297, "winograd_inferred": true}, "device": "nvidia_geforce_rtx_4090_tupi5"}
{"kind": "layer", "kernel_size": 9, "in_ch": 32, "out_ch": 32, "batch_size": 8, "input_resolution": 128, "precision": "fp32", "latency_ms": 0.5427813529968262, "winograd_speedup_info": {"speedup_ratio": 3.8759011611909084, "winograd_inferred": true}, "device": "nvidia_geforce_rtx_4090_tupi5"}
{"kind": "layer", "kernel_size": 9, "in_ch": 32, "out_ch": 32, "batch_size": 8, "input_resolution": 128, "precision": "int8", "latency_ms": 0.5443024635314941, "winograd_speedup_info": {"speedup_ratio": 3.8804162307988768, "winograd_inferred": true}, "device": "nvidia_geforce_rtx_4090_tupi5"}
{"kind": "layer", "kernel_size": 9, "in_ch": 64, "out_ch": 64, "batch_size": 1, "input_resolution": 64, "precision": "fp32", "latency_ms": 0.06183743476867676, "winograd_speedup_info": {"speedup_ratio": 1.2563117901789362, "winograd_inferred": false}, "device": "nvidia_geforce_rtx_4090_tupi5"}
{"kind": "layer", "kernel_size": 9, "in_ch": 64, "out_ch": 64, "batch_size": 1, "input_resolution": 64, "precision": "int8", "latency_ms": 0.05954623222351074, "winograd_speedup_info": {"speedup_ratio": 1.2541418428140048, "winograd_inferred": false}, "device": "nvidia_geforce_rtx_4090_tupi5"}
{"kind": "layer", "kernel_size": 9, "in_ch": 64, "out_ch": 64, "batch_size": 1, "input_resolution": 128, "precision": "fp32", "latency_ms": 0.134507417678833, "winograd_speedup_info": {"speedup_ratio": 2.9667866492146597, "winograd_inferred": true}, "device": "nvidia_geforce_rtx_4090_tupi5"}
{"kind": "layer", "kernel_size": 9, "in_ch": 64, "out_ch": 64, "batch_size": 1, "input_resolution": 128, "precision": "int8", "latency_ms": 0.13456463813781738, "winograd_speedup_info": {"speedup_ratio": 2.974495653600131, "winograd_inferred": true}, "device": "nvidia_geforce_rtx_4090_tupi5"}
{"kind": "layer", "kernel_size": 9, "in_ch": 64, "out_ch": 64, "batch_size": 8, "input_resolution": 64, "precision": "fp32", "latency_ms": 0.7088303565979004, "winograd_speedup_info": {"speedup_ratio": 2.765199293642785, "winograd_inferred": true}, "device": "nvidia_geforce_rtx_4090_tupi5"}
{"kind": "layer", "kernel_size": 9, "in_ch": 64, "out_ch": 64, "batch_size": 8, "input_resolution": 64, "precision": "int8", "latency_ms": 0.7086575031280518, "winograd_speedup_info": {"speedup_ratio": 2.768134224801312, "winograd_inferred": true}, "device": "nvidia_geforce_rtx_4090_tupi5"}
{"kind": "layer", "kernel_size": 9, "in_ch": 64, "out_ch": 64, "batch_size": 8, "input_resolution": 128, "precision": "fp32", "latency_ms": 2.836059331893921, "winograd_speedup_info": {"speedup_ratio": 3.261806145567828, "winograd_inferred": true}, "device": "nvidia_geforce_rtx_4090_tupi5"}
{"kind": "layer", "kernel_size": 9, "in_ch": 64, "out_ch": 64, "batch_size": 8, "input_resolution": 128, "precision": "int8", "latency_ms": 2.830146551132202, "winograd_speedup_info": {"speedup_ratio": 3.2786777854499745, "winograd_inferred": true}, "device": "nvidia_geforce_rtx_4090_tupi5"}
{"kind": "layer", "kernel_size": 9, "in_ch": 128, "out_ch": 128, "batch_size": 1, "input_resolution": 64, "precision": "fp32", "latency_ms": 0.1368427276611328, "winograd_speedup_info": {"speedup_ratio": 1.7040690505548706, "winograd_inferred": false}, "device": "nvidia_geforce_rtx_4090_tupi5"}
{"kind": "layer", "kernel_size": 9, "in_ch": 128, "out_ch": 128, "batch_size": 1, "input_resolution": 64, "precision": "int8", "latency_ms": 0.13701558113098145, "winograd_speedup_info": {"speedup_ratio": 1.7054901637994897, "winograd_inferred": false}, "device": "nvidia_geforce_rtx_4090_tupi5"}
{"kind": "layer", "kernel_size": 9, "in_ch": 128, "out_ch": 128, "batch_size": 1, "input_resolution": 128, "precision": "fp32", "latency_ms": 0.5126464366912842, "winograd_speedup_info": {"speedup_ratio": 2.3900024232353654, "winograd_inferred": true}, "device": "nvidia_geforce_rtx_4090_tupi5"}
{"kind": "layer", "kernel_size": 9, "in_ch": 128, "out_ch": 128, "batch_size": 1, "input_resolution": 128, "precision": "int8", "latency_ms": 0.5130302906036377, "winograd_speedup_info": {"speedup_ratio": 2.3887273230854453, "winograd_inferred": true}, "device": "nvidia_geforce_rtx_4090_tupi5"}
{"kind": "layer", "kernel_size": 9, "in_ch": 128, "out_ch": 128, "batch_size": 8, "input_resolution": 64, "precision": "fp32", "latency_ms": 1.018596887588501, "winograd_speedup_info": {"speedup_ratio": 3.833961203261175, "winograd_inferred": true}, "device": "nvidia_geforce_rtx_4090_tupi5"}
{"kind": "layer", "kernel_size": 9, "in_ch": 128, "out_ch": 128, "batch_size": 8, "input_resolution": 64, "precision": "int8", "latency_ms": 1.017754077911377, "winograd_speedup_info": {"speedup_ratio": 3.8350175293875024, "winograd_inferred": true}, "device": "nvidia_geforce_rtx_4090_tupi5"}
{"kind": "layer", "kernel_size": 9, "in_ch": 128, "out_ch": 128, "batch_size": 8, "input_resolution": 128, "precision": "fp32", "latency_ms": 4.161040782928467, "winograd_speedup_info": {"speedup_ratio": 2.24802733768251, "winograd_inferred": true}, "device": "nvidia_geforce_rtx_4090_tupi5"}
{"kind": "layer", "kernel_size": 9, "in_ch": 128, "out_ch": 128, "batch_size": 8, "input_resolution": 128, "precision": "int8", "latency_ms": 4.15967583656311, "winograd_speedup_info": {"speedup_ratio": 2.2469893082591175, "winograd_inferred": true}, "device": "nvidia_geforce_rtx_4090_tupi5"}
{"kind": "layer", "kernel_size": 11, "in_ch": 16, "out_ch": 16, "batch_size": 1, "input_resolution": 64, "precision": "fp32", "latency_ms": 0.0625145435333252, "winograd_speedup_info": {"speedup_ratio": 1.25720675944334, "winograd_inferred": false}, "device": "nvidia_geforce_rtx_4090_tupi5"}
{"kind": "layer", "kernel_size": 11, "in_ch": 16, "out_ch": 16, "batch_size": 1, "input_resolution": 64, "precision": "int8", "latency_ms": 0.06252050399780273, "winograd_speedup_info": {"speedup_ratio": 1.2600826446280993, "winograd_inferred": false}, "device": "nvidia_geforce_rtx_4090_tupi5"}
{"kind": "layer", "kernel_size": 11, "in_ch": 16, "out_ch": 16, "batch_size": 1, "input_resolution": 128, "precision": "fp32", "latency_ms": 0.22931337356567383, "winograd_speedup_info": {"speedup_ratio": 1.240170729705327, "winograd_inferred": false}, "device": "nvidia_geforce_rtx_4090_tupi5"}
{"kind": "layer", "kernel_size": 11, "in_ch": 16, "out_ch": 16, "batch_size": 1, "input_resolution": 128, "precision": "int8", "latency_ms": 0.2290797233581543, "winograd_speedup_info": {"speedup_ratio": 1.236301089360308, "winograd_inferred": false}, "device": "nvidia_geforce_rtx_4090_tupi5"}
{"kind": "layer", "kernel_size": 11, "in_ch": 16, "out_ch": 16, "batch_size": 8, "input_resolution": 64, "precision": "fp32", "latency_ms": 0.20137310028076172, "winograd_speedup_info": {"speedup_ratio": 1.6873510314785896, "winograd_inferred": false}, "device": "nvidia_geforce_rtx_4090_tupi5"}
{"kind": "layer", "kernel_size": 11, "in_ch": 16, "out_ch": 16, "batch_size": 8, "input_resolution": 64, "precision": "int8", "latency_ms": 0.2014148235321045, "winograd_speedup_info": {"speedup_ratio": 1.6891558334704624, "winograd_inferred": false}, "device": "nvidia_geforce_rtx_4090_tupi5"}
{"kind": "layer", "kernel_size": 11, "in_ch": 16, "out_ch": 16, "batch_size": 8, "input_resolution": 128, "precision": "fp32", "latency_ms": 0.7843661308288574, "winograd_speedup_info": {"speedup_ratio": 2.2233127839065543, "winograd_inferred": true}, "device": "nvidia_geforce_rtx_4090_tupi5"}
{"kind": "layer", "kernel_size": 11, "in_ch": 16, "out_ch": 16, "batch_size": 8, "input_resolution": 128, "precision": "int8", "latency_ms": 0.7843983173370361, "winograd_speedup_info": {"speedup_ratio": 2.229406986190089, "winograd_inferred": true}, "device": "nvidia_geforce_rtx_4090_tupi5"}
{"kind": "layer", "kernel_size": 11, "in_ch": 32, "out_ch": 32, "batch_size": 1, "input_resolution": 64, "precision": "fp32", "latency_ms": 0.054895877838134766, "winograd_speedup_info": {"speedup_ratio": 1.264865308804205, "winograd_inferred": false}, "device": "nvidia_geforce_rtx_4090_tupi5"}
{"kind": "layer", "kernel_size": 11, "in_ch": 32, "out_ch": 32, "batch_size": 1, "input_resolution": 64, "precision": "int8", "latency_ms": 0.05494236946105957, "winograd_speedup_info": {"speedup_ratio": 1.2752561006079788, "winograd_inferred": false}, "device": "nvidia_geforce_rtx_4090_tupi5"}
{"kind": "layer", "kernel_size": 11, "in_ch": 32, "out_ch": 32, "batch_size": 1, "input_resolution": 128, "precision": "fp32", "latency_ms": 0.10519146919250488, "winograd_speedup_info": {"speedup_ratio": 1.2471937730438345, "winograd_inferred": false}, "device": "nvidia_geforce_rtx_4090_tupi5"}
{"kind": "layer", "kernel_size": 11, "in_ch": 32, "out_ch": 32, "batch_size": 1, "input_resolution": 128, "precision": "int8", "latency_ms": 0.10527729988098145, "winograd_speedup_info": {"speedup_ratio": 1.2350764676862358, "winograd_inferred": false}, "device": "nvidia_geforce_rtx_4090_tupi5"}
{"kind": "layer", "kernel_size": 11, "in_ch": 32, "out_ch": 32, "batch_size": 8, "input_resolution": 64, "precision": "fp32", "latency_ms": 0.2029728889465332, "winograd_speedup_info": {"speedup_ratio": 1.8198655958039667, "winograd_inferred": true}, "device": "nvidia_geforce_rtx_4090_tupi5"}
{"kind": "layer", "kernel_size": 11, "in_ch": 32, "out_ch": 32, "batch_size": 8, "input_resolution": 64, "precision": "int8", "latency_ms": 0.2026677131652832, "winograd_speedup_info": {"speedup_ratio": 1.8259475458357313, "winograd_inferred": true}, "device": "nvidia_geforce_rtx_4090_tupi5"}
{"kind": "layer", "kernel_size": 11, "in_ch": 32, "out_ch": 32, "batch_size": 8, "input_resolution": 128, "precision": "fp32", "latency_ms": 0.7892894744873047, "winograd_speedup_info": {"speedup_ratio": 3.8810388467040826, "winograd_inferred": true}, "device": "nvidia_geforce_rtx_4090_tupi5"}
{"kind": "layer", "kernel_size": 11, "in_ch": 32, "out_ch": 32, "batch_size": 8, "input_resolution": 128, "precision": "int8", "latency_ms": 0.7891356945037842, "winograd_speedup_info": {"speedup_ratio": 3.873334801277111, "winograd_inferred": true}, "device": "nvidia_geforce_rtx_4090_tupi5"}
{"kind": "layer", "kernel_size": 11, "in_ch": 64, "out_ch": 64, "batch_size": 1, "input_resolution": 64, "precision": "fp32", "latency_ms": 0.08441329002380371, "winograd_speedup_info": {"speedup_ratio": 1.2639585560397995, "winograd_inferred": false}, "device": "nvidia_geforce_rtx_4090_tupi5"}
{"kind": "layer", "kernel_size": 11, "in_ch": 64, "out_ch": 64, "batch_size": 1, "input_resolution": 64, "precision": "int8", "latency_ms": 0.08488297462463379, "winograd_speedup_info": {"speedup_ratio": 1.2643923240938166, "winograd_inferred": false}, "device": "nvidia_geforce_rtx_4090_tupi5"}
{"kind": "layer", "kernel_size": 11, "in_ch": 64, "out_ch": 64, "batch_size": 1, "input_resolution": 128, "precision": "fp32", "latency_ms": 0.19594907760620117, "winograd_speedup_info": {"speedup_ratio": 2.9571428571428573, "winograd_inferred": true}, "device": "nvidia_geforce_rtx_4090_tupi5"}
{"kind": "layer", "kernel_size": 11, "in_ch": 64, "out_ch": 64, "batch_size": 1, "input_resolution": 128, "precision": "int8", "latency_ms": 0.19591093063354492, "winograd_speedup_info": {"speedup_ratio": 2.94392523364486, "winograd_inferred": true}, "device": "nvidia_geforce_rtx_4090_tupi5"}
{"kind": "layer", "kernel_size": 11, "in_ch": 64, "out_ch": 64, "batch_size": 8, "input_resolution": 64, "precision": "fp32", "latency_ms": 1.0387659072875977, "winograd_speedup_info": {"speedup_ratio": 2.766612028747951, "winograd_inferred": true}, "device": "nvidia_geforce_rtx_4090_tupi5"}
{"kind": "layer", "kernel_size": 11, "in_ch": 64, "out_ch": 64, "batch_size": 8, "input_resolution": 64, "precision": "int8", "latency_ms": 1.0401380062103271, "winograd_speedup_info": {"speedup_ratio": 2.762531486146096, "winograd_inferred": true}, "device": "nvidia_geforce_rtx_4090_tupi5"}
{"kind": "layer", "kernel_size": 11, "in_ch": 64, "out_ch": 64, "batch_size": 8, "input_resolution": 128, "precision": "fp32", "latency_ms": 4.146978855133057, "winograd_speedup_info": {"speedup_ratio": 3.3143139958284724, "winograd_inferred": true}, "device": "nvidia_geforce_rtx_4090_tupi5"}
{"kind": "layer", "kernel_size": 11, "in_ch": 64, "out_ch": 64, "batch_size": 8, "input_resolution": 128, "precision": "int8", "latency_ms": 4.1479575634002686, "winograd_speedup_info": {"speedup_ratio": 3.2924871840197985, "winograd_inferred": true}, "device": "nvidia_geforce_rtx_4090_tupi5"}
{"kind": "layer", "kernel_size": 11, "in_ch": 128, "out_ch": 128, "batch_size": 1, "input_resolution": 64, "precision": "fp32", "latency_ms": 0.19954323768615723, "winograd_speedup_info": {"speedup_ratio": 1.7095340029639388, "winograd_inferred": false}, "device": "nvidia_geforce_rtx_4090_tupi5"}
{"kind": "layer", "kernel_size": 11, "in_ch": 128, "out_ch": 128, "batch_size": 1, "input_resolution": 64, "precision": "int8", "latency_ms": 0.19965291023254395, "winograd_speedup_info": {"speedup_ratio": 1.7149942139196561, "winograd_inferred": false}, "device": "nvidia_geforce_rtx_4090_tupi5"}
{"kind": "layer", "kernel_size": 11, "in_ch": 128, "out_ch": 128, "batch_size": 1, "input_resolution": 128, "precision": "fp32", "latency_ms": 0.7592308521270752, "winograd_speedup_info": {"speedup_ratio": 2.3901266173112847, "winograd_inferred": true}, "device": "nvidia_geforce_rtx_4090_tupi5"}
{"kind": "layer", "kernel_size": 11, "in_ch": 128, "out_ch": 128, "batch_size": 1, "input_resolution": 128, "precision": "int8", "latency_ms": 0.7596898078918457, "winograd_speedup_info": {"speedup_ratio": 2.3899073049252904, "winograd_inferred": true}, "device": "nvidia_geforce_rtx_4090_tupi5"}
{"kind": "layer", "kernel_size": 11, "in_ch": 128, "out_ch": 128, "batch_size": 8, "input_resolution": 64, "precision": "fp32", "latency_ms": 1.5112018585205078, "winograd_speedup_info": {"speedup_ratio": 3.832952630593522, "winograd_inferred": true}, "device": "nvidia_geforce_rtx_4090_tupi5"}
{"kind": "layer", "kernel_size": 11, "in_ch": 128, "out_ch": 128, "batch_size": 8, "input_resolution": 64, "precision": "int8", "latency_ms": 1.5111160278320312, "winograd_speedup_info": {"speedup_ratio": 3.8313243991914354, "winograd_inferred": true}, "device": "nvidia_geforce_rtx_4090_tupi5"}
{"kind": "layer", "kernel_size": 11, "in_ch": 128, "out_ch": 128, "batch_size": 8, "input_resolution": 128, "precision": "fp32", "latency_ms": 6.1327064037323, "winograd_speedup_info": {"speedup_ratio": 2.2477868900133777, "winograd_inferred": true}, "device": "nvidia_geforce_rtx_4090_tupi5"}
{"kind": "layer", "kernel_size": 11, "in_ch": 128, "out_ch": 128, "batch_size": 8, "input_resolution": 128, "precision": "int8", "latency_ms": 6.133962869644165, "winograd_speedup_info": {"speedup_ratio": 2.2490932295768147, "winograd_inferred": true}, "device": "nvidia_geforce_rtx_4090_tupi5"}
{"kind": "fft", "kernel_size": 5, "in_ch": 16, "out_ch": 16, "latency_ms": 0.19612789154052734, "note": "FFT-based convolution; stride=1 only", "device": "nvidia_geforce_rtx_4090_tupi5"}
{"kind": "fft", "kernel_size": 5, "in_ch": 32, "out_ch": 32, "latency_ms": 0.19679665565490723, "note": "FFT-based convolution; stride=1 only", "device": "nvidia_geforce_rtx_4090_tupi5"}
{"kind": "fft", "kernel_size": 5, "in_ch": 64, "out_ch": 64, "latency_ms": 0.7489442825317383, "note": "FFT-based convolution; stride=1 only", "device": "nvidia_geforce_rtx_4090_tupi5"}
{"kind": "fft", "kernel_size": 5, "in_ch": 128, "out_ch": 128, "latency_ms": 3.7446975708007812, "note": "FFT-based convolution; stride=1 only", "device": "nvidia_geforce_rtx_4090_tupi5"}
{"kind": "fft", "kernel_size": 7, "in_ch": 16, "out_ch": 16, "latency_ms": 0.19576430320739746, "note": "FFT-based convolution; stride=1 only", "device": "nvidia_geforce_rtx_4090_tupi5"}
{"kind": "fft", "kernel_size": 7, "in_ch": 32, "out_ch": 32, "latency_ms": 0.1963496208190918, "note": "FFT-based convolution; stride=1 only", "device": "nvidia_geforce_rtx_4090_tupi5"}
{"kind": "fft", "kernel_size": 7, "in_ch": 64, "out_ch": 64, "latency_ms": 0.8036553859710693, "note": "FFT-based convolution; stride=1 only", "device": "nvidia_geforce_rtx_4090_tupi5"}
{"kind": "fft", "kernel_size": 7, "in_ch": 128, "out_ch": 128, "latency_ms": 3.959197998046875, "note": "FFT-based convolution; stride=1 only", "device": "nvidia_geforce_rtx_4090_tupi5"}
{"kind": "fft", "kernel_size": 9, "in_ch": 16, "out_ch": 16, "latency_ms": 0.1956796646118164, "note": "FFT-based convolution; stride=1 only", "device": "nvidia_geforce_rtx_4090_tupi5"}
{"kind": "fft", "kernel_size": 9, "in_ch": 32, "out_ch": 32, "latency_ms": 0.19619226455688477, "note": "FFT-based convolution; stride=1 only", "device": "nvidia_geforce_rtx_4090_tupi5"}
{"kind": "fft", "kernel_size": 9, "in_ch": 64, "out_ch": 64, "latency_ms": 0.8684170246124268, "note": "FFT-based convolution; stride=1 only", "device": "nvidia_geforce_rtx_4090_tupi5"}
{"kind": "fft", "kernel_size": 9, "in_ch": 128, "out_ch": 128, "latency_ms": 4.250929355621338, "note": "FFT-based convolution; stride=1 only", "device": "nvidia_geforce_rtx_4090_tupi5"}
{"kind": "fft", "kernel_size": 11, "in_ch": 16, "out_ch": 16, "latency_ms": 0.21219134330749512, "note": "FFT-based convolution; stride=1 only", "device": "nvidia_geforce_rtx_4090_tupi5"}
{"kind": "fft", "kernel_size": 11, "in_ch": 32, "out_ch": 32, "latency_ms": 0.21318554878234863, "note": "FFT-based convolution; stride=1 only", "device": "nvidia_geforce_rtx_4090_tupi5"}
{"kind": "fft", "kernel_size": 11, "in_ch": 64, "out_ch": 64, "latency_ms": 1.328040361404419, "note": "FFT-based convolution; stride=1 only", "device": "nvidia_geforce_rtx_4090_tupi5"}
{"kind": "fft", "kernel_size": 11, "in_ch": 128, "out_ch": 128, "latency_ms": 6.080976724624634, "note": "FFT-based convolution; stride=1 only", "device": "nvidia_geforce_rtx_4090_tupi5"}
{"kind": "model", "model": "alexnet_bottleneck", "precision": "fp32", "latency_ms": 0.3435695171356201, "throughput_img_s": 2910.6191036303767, "power_draw_avg_w": null, "power_draw_std_w": null, "gpu_utilization_pct": null, "gpu_memory_peak_mb": 12.22119140625, "compute_efficiency_gflops_s": 0.23680461723816007, "winograd_trace_detected": false, "device": "nvidia_geforce_rtx_4090_tupi5"}
{"kind": "model", "model": "alexnet_bottleneck", "precision": "int8", "latency_ms": 0.48135876655578613, "throughput_img_s": 2077.452556136436, "power_draw_avg_w": null, "power_draw_std_w": null, "gpu_utilization_pct": null, "gpu_memory_peak_mb": null, "compute_efficiency_gflops_s": 0.1690191467419158, "winograd_trace_detected": null, "device": "nvidia_geforce_rtx_4090_tupi5"}
{"kind": "model", "model": "alexnet_final_bottleneck_residual", "precision": "fp32", "latency_ms": 0.6183171272277832, "throughput_img_s": 1617.2930620302998, "power_draw_avg_w": null, "power_draw_std_w": null, "gpu_utilization_pct": null, "gpu_memory_peak_mb": 12.98974609375, "compute_efficiency_gflops_s": 0.180522406843956, "winograd_trace_detected": false, "device": "nvidia_geforce_rtx_4090_tupi5"}
{"kind": "model", "model": "alexnet_final_bottleneck_residual", "precision": "int8", "latency_ms": 1.2581968307495117, "throughput_img_s": 794.7882044849032, "power_draw_avg_w": null, "power_draw_std_w": null, "gpu_utilization_pct": null, "gpu_memory_peak_mb": null, "compute_efficiency_gflops_s": 0.08871433568427252, "winograd_trace_detected": null, "device": "nvidia_geforce_rtx_4090_tupi5"}
